openacli/__init__.py
openacli/openacli.py
openacli-0.2.dist-info/LICENSE
openacli-0.2.dist-info/METADATA
openacli-0.2.dist-info/WHEEL
openacli-0.2.dist-info/entry_points.txt
openacli-0.2.dist-info/top_level.txt
openacli-0.2.dist-info/RECORD
