Metadata-Version: 2.1
Name: openacli
Version: 0.2
Summary: OpenAI CLI Interface
Home-page: https://github.com/cdrew3/openacli
Author: Chris Drew
Author-email: chris.drew.cd@gmail.com
License: MIT
License-File: LICENSE
Requires-Dist: aiohttp (==3.8.3)
Requires-Dist: aiosignal (==1.3.1)
Requires-Dist: async-timeout (==4.0.2)
Requires-Dist: attrs (==22.2.0)
Requires-Dist: certifi (==2022.12.7)
Requires-Dist: charset-normalizer (==2.1.1)
Requires-Dist: colorama (==0.4.3)
Requires-Dist: frozenlist (==1.3.3)
Requires-Dist: getch (==1.0)
Requires-Dist: idna (==3.4)
Requires-Dist: multidict (==6.0.4)
Requires-Dist: openai (==0.26.4)
Requires-Dist: pillow (==9.4.0)
Requires-Dist: requests (==2.28.2)
Requires-Dist: smartinput (==1.0.8)
Requires-Dist: tqdm (==4.64.1)
Requires-Dist: urllib3 (==1.26.14)
Requires-Dist: yarl (==1.8.2)
